AUTHORS
ChangeLog
Makefile
README.rst
requirements.txt
setup.cfg
setup.py
Strip.egg-info/PKG-INFO
Strip.egg-info/SOURCES.txt
Strip.egg-info/dependency_links.txt
Strip.egg-info/not-zip-safe
Strip.egg-info/pbr.json
Strip.egg-info/requires.txt
Strip.egg-info/top_level.txt
strip/Apc.py
strip/Connect.py
strip/Outlets.py
strip/PowerManagement.py
strip/PowerStrip.py
strip/ServerTech.py
strip/Strips.py
strip/__init__.py
tests/README.md
tests/testing-apc.py
tests/testing-servertech.py