Metadata-Version: 1.1
Name: Strip
Version: 0.0.1.dev12
Summary: Automated powerstrip management
Home-page: https://github.com/jtaleric/Strip
Author: Joe Talerico
Author-email: rook@redhat.com
License: Apache-2
Platform: UNKNOWN
Classifier: Development Status :: 3 - Alpha
Classifier: Intended Audience :: Developers
Classifier: Intended Audience :: Information Technology
Classifier: Intended Audience :: System Administrators
Classifier: License :: OSI Approved :: Apache Software License
Classifier: Programming Language :: Python
Classifier: Programming Language :: Python :: 2
Classifier: Programming Language :: Python :: 2.7
Classifier: Programming Language :: Python :: 3
Classifier: Programming Language :: Python :: 3.0
